cryptofeed-2.4.0.dist-info/LICENSE
cryptofeed-2.4.0.dist-info/METADATA
cryptofeed-2.4.0.dist-info/AUTHORS.md
cryptofeed-2.4.0.dist-info/WHEEL
cryptofeed-2.4.0.dist-info/RECORD
cryptofeed-2.4.0.dist-info/top_level.txt
cryptofeed/feed.py
cryptofeed/feedhandler.py
cryptofeed/exchange.py
cryptofeed/__init__.py
cryptofeed/symbols.py
cryptofeed/raw_data_collection.py
cryptofeed/config.py
cryptofeed/defines.py
cryptofeed/types.cpython-39-x86_64-linux-gnu.so
cryptofeed/nbbo.py
cryptofeed/connection.py
cryptofeed/log.py
cryptofeed/callback.py
cryptofeed/connection_handler.py
cryptofeed/exceptions.py
cryptofeed/exchanges/ftx.py
cryptofeed/exchanges/kraken.py
cryptofeed/exchanges/gemini.py
cryptofeed/exchanges/binance_tr.py
cryptofeed/exchanges/binance_delivery.py
cryptofeed/exchanges/__init__.py
cryptofeed/exchanges/exx.py
cryptofeed/exchanges/deribit.py
cryptofeed/exchanges/bitfinex.py
cryptofeed/exchanges/gateio_futures.py
cryptofeed/exchanges/kraken_futures.py
cryptofeed/exchanges/ftx_tr.py
cryptofeed/exchanges/binance.py
cryptofeed/exchanges/bitdotcom.py
cryptofeed/exchanges/hitbtc.py
cryptofeed/exchanges/huobi.py
cryptofeed/exchanges/bitmex.py
cryptofeed/exchanges/ftx_us.py
cryptofeed/exchanges/okcoin.py
cryptofeed/exchanges/coinbase.py
cryptofeed/exchanges/upbit.py
cryptofeed/exchanges/okx.py
cryptofeed/exchanges/bitget.py
cryptofeed/exchanges/gateio.py
cryptofeed/exchanges/independent_reserve.py
cryptofeed/exchanges/phemex.py
cryptofeed/exchanges/poloniex.py
cryptofeed/exchanges/bithumb.py
cryptofeed/exchanges/bequant.py
cryptofeed/exchanges/binance_us.py
cryptofeed/exchanges/fmfw.py
cryptofeed/exchanges/dydx.py
cryptofeed/exchanges/probit.py
cryptofeed/exchanges/bitstamp.py
cryptofeed/exchanges/delta.py
cryptofeed/exchanges/cryptodotcom.py
cryptofeed/exchanges/blockchain.py
cryptofeed/exchanges/ascendex.py
cryptofeed/exchanges/kucoin.py
cryptofeed/exchanges/bitflyer.py
cryptofeed/exchanges/huobi_dm.py
cryptofeed/exchanges/huobi_swap.py
cryptofeed/exchanges/binance_futures.py
cryptofeed/exchanges/ascendex_futures.py
cryptofeed/exchanges/bybit.py
cryptofeed/exchanges/bittrex.py
cryptofeed/exchanges/mixins/ftx_rest.py
