Metadata-Version: 2.1
Name: cryptofeed
Version: 2.4.0
Summary: Cryptocurrency Exchange Websocket Data Feed Handler
Home-page: https://github.com/bmoscon/cryptofeed
Author: Bryant Moscon
Author-email: bmoscon@gmail.com
License: XFree86
Keywords: cryptocurrency,bitcoin,btc,feed handler,market feed,market data,crypto assets,Trades,Tickers,BBO,Funding,Open Interest,Liquidation,Order book,Bid,Ask,fmfw.io,Bitfinex,bitFlyer,AscendEX,Bitstamp,Blockchain.com,Bybit,Binance,Binance Delivery,Binance Futures,Binance US,BitMEX,Coinbase,Deribit,EXX,Gate.io,Gemini,HitBTC,Huobi,Huobi DM,Huobi Swap,Kraken,Kraken Futures,OKCoin,OKX,Poloniex,ProBit,Upbit
Classifier: Intended Audience :: Developers
Classifier: Development Status :: 4 - Beta
Classifier: Programming Language :: Python :: 3 :: Only
Classifier: Programming Language :: Python :: 3.8
Classifier: Programming Language :: Python :: 3.9
Classifier: Programming Language :: Python :: 3.10
Classifier: Framework :: AsyncIO
Requires-Python: >=3.8
License-File: LICENSE
License-File: AUTHORS.md
Requires-Dist: requests >=2.18.4
Requires-Dist: websockets >=10.0
Requires-Dist: pyyaml
Requires-Dist: aiohttp ==3.9.1
Requires-Dist: aiofile >=2.0.0
Requires-Dist: yapic.json >=1.6.3
Requires-Dist: order-book >=0.6.0
Requires-Dist: aiodns >=1.1
Requires-Dist: uvloop ; platform_system != "Windows"
Provides-Extra: all
Requires-Dist: arctic ; extra == 'all'
Requires-Dist: google-cloud-pubsub >=2.4.1 ; extra == 'all'
Requires-Dist: gcloud-aio-pubsub ; extra == 'all'
Requires-Dist: aiokafka >=0.7.0 ; extra == 'all'
Requires-Dist: motor ; extra == 'all'
Requires-Dist: asyncpg ; extra == 'all'
Requires-Dist: aio-pika ; extra == 'all'
Requires-Dist: pika ; extra == 'all'
Requires-Dist: hiredis ; extra == 'all'
Requires-Dist: redis >=4.5.1 ; extra == 'all'
Requires-Dist: pyzmq ; extra == 'all'
Provides-Extra: arctic
Requires-Dist: arctic ; extra == 'arctic'
Requires-Dist: pandas ; extra == 'arctic'
Provides-Extra: gcp_pubsub
Requires-Dist: google-cloud-pubsub >=2.4.1 ; extra == 'gcp_pubsub'
Requires-Dist: gcloud-aio-pubsub ; extra == 'gcp_pubsub'
Provides-Extra: kafka
Requires-Dist: aiokafka >=0.7.0 ; extra == 'kafka'
Provides-Extra: mongo
Requires-Dist: motor ; extra == 'mongo'
Provides-Extra: postgres
Requires-Dist: asyncpg ; extra == 'postgres'
Provides-Extra: rabbit
Requires-Dist: aio-pika ; extra == 'rabbit'
Requires-Dist: pika ; extra == 'rabbit'
Provides-Extra: redis
Requires-Dist: hiredis ; extra == 'redis'
Requires-Dist: redis >=4.5.1 ; extra == 'redis'
Provides-Extra: zmq
Requires-Dist: pyzmq ; extra == 'zmq'
